.coveragerc
LICENSE
MANIFEST.in
README.md
dev_requirements.txt
requirements.txt
setup.cfg
setup.py
versioneer.py
csirtg_geo/__init__.py
csirtg_geo/_version.py
csirtg_geo/constants.py
csirtg_geo.egg-info/PKG-INFO
csirtg_geo.egg-info/SOURCES.txt
csirtg_geo.egg-info/dependency_links.txt
csirtg_geo.egg-info/entry_points.txt
csirtg_geo.egg-info/requires.txt
csirtg_geo.egg-info/top_level.txt
test/test_basics.py