Metadata-Version: 1.1
Name: csirtg-geo
Version: 0.1
Summary: CSIRTG Geo Utils
Home-page: https://github.com/csirtgadgets/csirtg-geo
Author: Wes Young
Author-email: wes@csirtgadgets.com
License: MPL2
Keywords: security
Platform: UNKNOWN
Classifier: Programming Language :: Python
